[
  {
    "title": "Chuyên đề 1: Nền tảng, Lịch sử & Phương pháp luận",
    "blocks": [
      {
        "type": "timeline",
        "title": "Lịch sử hình thành Kinh tế chính trị",
        "data": {
          "items": [
            {
              "time": "Thời Cổ đại - thế kỷ XV",
              "content": "Tư tưởng kinh tế tản mạn trong triết học, luận lý. Chưa trở thành khoa học độc lập."
            },
            {
              "time": "Thế kỷ XV - XVII",
              "content": "Chủ nghĩa trọng thương (Anh, Ý, Pháp). Coi lưu thông, thương mại là nguồn gốc của cải."
            },
            {
              "time": "Thế kỷ XVII - XVIII",
              "content": "Chủ nghĩa trọng nông (Pháp). Chuyển hướng nghiên cứu từ lưu thông sang lĩnh vực sản xuất nông nghiệp."
            },
            {
              "time": "Cuối TK XVIII - nửa đầu TK XIX",
              "content": "KTCT Cổ điển Anh (A.Smith, D.Ricardo). Rút ra kết luận khoa học: giá trị do hao phí lao động tạo ra."
            },
            {
              "time": "Nửa cuối TK XIX",
              "content": "Lý luận KTCT của C.Mác và Ph.Ăngghen. Sáng lập hệ thống lý luận KTCT mang tính cách mạng, khoa học, toàn diện."
            },
            {
              "time": "Cuối TK XIX - nay",
              "content": "V.I.Lênin và các Đảng Cộng sản tiếp tục kế thừa, bảo vệ và phát triển lý luận KTCT trong thời đại mới."
            }
          ]
        }
      },
      {
        "type": "mindmap",
        "title": "Tổng quan Kinh tế chính trị Mác - Lênin (Chương 1)",
        "data": {
          "root": "Kinh tế chính trị Mác - Lênin",
          "children": [
            {
              "title": "Lịch sử phát triển",
              "content": "Từ tư tưởng Cổ đại -> Trọng thương -> Trọng nông -> Cổ điển Anh -> Mác-Lênin"
            },
            {
              "title": "Đối tượng nghiên cứu",
              "content": "Chỉnh thể thống nhất các quan hệ xã hội của sản xuất và trao đổi"
            },
            {
              "title": "Phương pháp nghiên cứu",
              "content": "Trừu tượng hóa khoa học (chủ yếu), Biện chứng duy vật, Liên ngành"
            },
            {
              "title": "Chức năng",
              "content": "Nhận thức, Thực tiễn, Tư tưởng, Phương pháp luận"
            }
          ]
        }
      },
      {
        "type": "vs-wrap",
        "title": "So sánh Đối tượng nghiên cứu của các Trường phái",
        "data": {
          "col1_title": "Các trường phái kinh tế trước Mác",
          "col1_desc": "- Chủ nghĩa trọng thương: Tập trung trong lĩnh vực lưu thông.\n- Chủ nghĩa trọng nông: Chỉ nghiên cứu quan hệ kinh tế ở lĩnh vực nông nghiệp.\n- KTCT cổ điển Anh: Chỉ nghiên cứu chung trong nền sản xuất.",
          "col2_title": "Kinh tế chính trị Mác - Lênin",
          "col2_desc": "Nghiên cứu các quan hệ xã hội của sản xuất và trao đổi, luôn đặt trong mối liên hệ biện chứng chặt chẽ với trình độ Lực lượng sản xuất và Kiến trúc thượng tầng."
        }
      },
      {
        "type": "pyramid",
        "title": "Mục đích nghiên cứu của Kinh tế chính trị Mác - Lênin",
        "data": {
          "levels": [
            {
              "title": "Mục đích xuyên suốt",
              "description": "Thúc đẩy sự giàu có, cung cấp cơ sở khoa học góp phần phát triển toàn diện xã hội, nâng cao văn minh nhân loại."
            },
            {
              "title": "Cấp độ cốt lõi cao nhất",
              "description": "Phát hiện ra các quy luật kinh tế khách quan chi phối quan hệ giữa người với người trong quá trình sản xuất và trao đổi."
            }
          ]
        }
      },
      {
        "type": "flowchart",
        "title": "Phương pháp Trừu tượng hóa khoa học",
        "data": {
          "steps": [
            {
              "label": "Bước 1: Tiếp cận đối tượng",
              "description": "Khảo sát các hiện tượng, quá trình kinh tế phức tạp đan xen trong thực tiễn."
            },
            {
              "label": "Bước 2: Gạt bỏ yếu tố ngẫu nhiên",
              "description": "Nhận ra và loại bỏ những hiện tượng tạm thời, gián tiếp (đảm bảo không làm sai lệch bản chất)."
            },
            {
              "label": "Bước 3: Tách lọc bản chất",
              "description": "Tách ra được những dấu hiệu điển hình, bền vững, ổn định, trực tiếp nhất."
            },
            {
              "label": "Bước 4: Khái quát quy luật",
              "description": "Hình thành các phạm trù kinh tế và rút ra các quy luật kinh tế khách quan."
            }
          ]
        }
      },
      {
        "type": "features",
        "title": "4 Chức năng của Kinh tế chính trị Mác - Lênin",
        "data": {
          "items": [
            {
              "title": "Chức năng Nhận thức",
              "description": "Cung cấp hệ thống tri thức lý luận, phạm trù, quy luật chi phối sự vận động của sản xuất và trao đổi."
            },
            {
              "title": "Chức năng Thực tiễn",
              "description": "Người lao động và nhà quản lý vận dụng quy luật kinh tế vào hoạch định chính sách và quản trị quốc gia."
            },
            {
              "title": "Chức năng Tư tưởng",
              "description": "Xây dựng lý tưởng khoa học tiến bộ, niềm tin phấn đấu vì mục tiêu dân giàu, nước mạnh, xóa bỏ áp bức."
            },
            {
              "title": "Chức năng Phương pháp luận",
              "description": "Làm nền tảng lý luận cốt lõi cho việc nghiên cứu các môn khoa học kinh tế chuyên ngành khác."
            }
          ]
        }
      },
      {
        "type": "t-account",
        "title": "Phân biệt Quy luật kinh tế và Chính sách kinh tế",
        "data": {
          "left_title": "Quy luật kinh tế (Khách quan)",
          "left_content": "- Tồn tại khách quan, độc lập với ý chí con người.\n- Bị chi phối bởi những lực lượng tự nhiên của nền kinh tế.\n- Điều chỉnh hành vi con người thông qua động cơ lợi ích.",
          "right_title": "Chính sách kinh tế (Chủ quan)",
          "right_content": "- Sự vận dụng chủ quan của nhà nước dựa trên nhận thức quy luật.\n- Có thể phù hợp (thúc đẩy phát triển) hoặc không phù hợp (kìm hãm) với quy luật khách quan."
        }
      },
      {
        "type": "matrix-table",
        "title": "Đóng góp của các Vĩ nhân đối với Kinh tế chính trị",
        "data": {
          "headers": [
            "Nhà tư tưởng",
            "Giai đoạn lịch sử",
            "Đóng góp cốt lõi"
          ],
          "rows": [
            [
              "C.Mác",
              "Nửa cuối thế kỷ XIX",
              "Xây dựng hệ thống lý luận cách mạng, khoa học, toàn diện; tìm ra quy luật chi phối phương thức sản xuất TBCN."
            ],
            [
              "Ph.Ăngghen",
              "Nửa cuối thế kỷ XIX",
              "Cùng C.Mác biên soạn, công bố lý luận KTCT - trở thành 1 trong 3 bộ phận cấu thành Chủ nghĩa Mác."
            ],
            [
              "V.I.Lênin",
              "Cuối TK XIX - Đầu TK XX",
              "Chỉ ra đặc điểm kinh tế của độc quyền, độc quyền nhà nước và các vấn đề KTCT thời kỳ quá độ lên CNXH."
            ]
          ]
        }
      },
      {
        "type": "onion",
        "title": "Hệ thống Quan hệ kinh tế trong KTCT Mác - Lênin",
        "data": {
          "layers": [
            {
              "name": "Lớp lõi: Lực lượng sản xuất",
              "description": "Trình độ vật chất, kỹ thuật, công cụ lao động (Quyết định các quan hệ khác)."
            },
            {
              "name": "Lớp giữa: Quan hệ sản xuất và trao đổi",
              "description": "Đối tượng nghiên cứu trực tiếp của KTCT, là cầu nối biện chứng."
            },
            {
              "name": "Lớp vỏ ngoài: Kiến trúc thượng tầng",
              "description": "Hệ thống thiết chế chính trị, pháp luật, văn hóa phản ánh cơ sở hạ tầng."
            }
          ]
        }
      },
      {
        "type": "flip-card",
        "title": "Các Thuật ngữ Cốt lõi Chương 1",
        "data": {
          "cards": [
            {
              "front": "Kinh tế chính trị (Nghĩa hẹp)",
              "back": "Là khoa học nghiên cứu quan hệ sản xuất và trao đổi trong MỘT phương thức sản xuất nhất định."
            },
            {
              "front": "Chủ nghĩa trọng thương",
              "back": "Trường phái tư tưởng kinh tế đầu tiên, coi lĩnh vực lưu thông (thương mại) mới là nguồn gốc của cải."
            },
            {
              "front": "Trừu tượng hóa khoa học",
              "back": "Phương pháp cốt lõi: gạt bỏ những hiện tượng ngẫu nhiên, tạm thời để tìm ra bản chất bền vững của sự vật."
            }
          ]
        }
      },
      {
        "type": "quadrant",
        "title": "Đối tượng nghiên cứu: Nghĩa Hẹp vs Nghĩa Rộng",
        "data": {
          "q1_title": "Nghĩa Hẹp (Khái niệm)",
          "q1_content": "Nghiên cứu quan hệ sản xuất và trao đổi trong MỘT phương thức sản xuất cụ thể.",
          "q2_title": "Nghĩa Rộng (Khái niệm)",
          "q2_content": "Nghiên cứu quy luật chi phối sự sản xuất/trao đổi trong TOÀN BỘ lịch sử xã hội loài người.",
          "q3_title": "Nghĩa Hẹp (Mục tiêu)",
          "q3_content": "Phân tích sâu sắc bản chất, mâu thuẫn đặc thù của một giai đoạn lịch sử (VD: CNTB).",
          "q4_title": "Nghĩa Rộng (Mục tiêu)",
          "q4_content": "Phản ánh tính phổ quát, quy luật chung của sự phát triển kinh tế qua các thời kỳ."
        }
      },
      {
        "type": "process-steps",
        "title": "Quá trình Nhận thức Quy luật Kinh tế",
        "data": {
          "steps": [
            {
              "title": "1. Hiện tượng kinh tế",
              "description": "Quan sát các hoạt động sản xuất, trao đổi phong phú trên bề mặt xã hội."
            },
            {
              "title": "2. Phạm trù kinh tế",
              "description": "Dùng trừu tượng hóa khái quát các hiện tượng thành các khái niệm cơ bản."
            },
            {
              "title": "3. Quy luật kinh tế",
              "description": "Phát hiện mối liên hệ bản chất, tất yếu, lặp đi lặp lại chi phối các hiện tượng."
            },
            {
              "title": "4. Vận dụng thực tiễn",
              "description": "Biến nhận thức quy luật thành các chính sách kinh tế thúc đẩy tiến bộ xã hội."
            }
          ]
        }
      }
    ]
  },
  {
    "title": "Chuyên đề 2: Các Quy Luật Kinh Tế Xuyên Suốt",
    "blocks": [
      {
        "type": "mindmap",
        "title": "Bản Đồ Hệ Thống Các Quy Luật Kinh Tế Trong Mác - Lênin",
        "data": {
          "root": "Các Quy Luật Kinh Tế",
          "branches": [
            {
              "name": "Sản xuất Hàng hóa",
              "details": [
                "Quy luật giá trị (Cơ bản)",
                "Quy luật cung cầu",
                "Quy luật cạnh tranh",
                "Quy luật lưu thông tiền tệ"
              ]
            },
            {
              "name": "Chủ nghĩa Tư bản tự do cạnh tranh",
              "details": [
                "Quy luật giá trị thặng dư (Tuyệt đối)",
                "Quy luật tích lũy tư bản",
                "Quy luật lợi nhuận bình quân"
              ]
            },
            {
              "name": "Chủ nghĩa Tư bản độc quyền",
              "details": [
                "Quy luật độc quyền",
                "Quy luật lợi nhuận độc quyền cao"
              ]
            }
          ]
        }
      },
      {
        "type": "formula",
        "title": "Quy Luật Lưu Thông Tiền Tệ",
        "data": {
          "equation": "M = (P × Q) / V",
          "variables": [
            {
              "symbol": "M",
              "meaning": "Số lượng tiền cần thiết cho lưu thông"
            },
            {
              "symbol": "P",
              "meaning": "Mức giá cả trung bình của 1 đơn vị hàng hóa"
            },
            {
              "symbol": "Q",
              "meaning": "Khối lượng hàng hóa mang ra lưu thông"
            },
            {
              "symbol": "V",
              "meaning": "Số vòng luân chuyển trung bình của 1 đơn vị tiền tệ"
            }
          ],
          "note": "Nếu tiền giấy phát hành vượt quá M -> Lạm phát."
        }
      },
      {
        "type": "features",
        "title": "Quy Luật Giá Trị: Nội Dung & Yêu Cầu",
        "data": {
          "items": [
            {
              "name": "Nội dung cơ bản",
              "desc": "Sản xuất và trao đổi hàng hóa phải dựa trên cơ sở hao phí lao động xã hội cần thiết."
            },
            {
              "name": "Yêu cầu trong sản xuất",
              "desc": "Hao phí lao động cá biệt < hoặc = Hao phí lao động xã hội cần thiết."
            },
            {
              "name": "Yêu cầu trong trao đổi",
              "desc": "Phải thực hiện theo nguyên tắc ngang giá (Tổng giá cả = Tổng giá trị)."
            }
          ]
        }
      },
      {
        "type": "cycle",
        "title": "Cơ Chế Tác Động Của Quy Luật Giá Trị",
        "data": {
          "steps": [
            "Điều tiết sản xuất và lưu thông hàng hóa qua biến động của giá cả thị trường.",
            "Kích thích cải tiến kỹ thuật, hợp lý hóa sản xuất, tăng năng suất lao động.",
            "Phân hóa những người sản xuất hàng hóa thành người giàu và người nghèo."
          ]
        }
      },
      {
        "type": "vs-wrap",
        "title": "So Sánh Giá Trị & Giá Cả Hàng Hóa",
        "data": {
          "left": {
            "title": "Giá Trị Hàng Hóa",
            "points": [
              "Lao động xã hội của người sản xuất kết tinh trong hàng hóa",
              "Là nội dung, cơ sở của giá cả",
              "Quyết định giá cả thị trường"
            ]
          },
          "right": {
            "title": "Giá Cả Hàng Hóa",
            "points": [
              "Biểu hiện bằng tiền của giá trị hàng hóa",
              "Là hình thức biểu hiện của giá trị",
              "Chịu tác động của Cung - Cầu, Cạnh tranh, Sức mua của tiền"
            ]
          }
        }
      },
      {
        "type": "onion",
        "title": "Cấu Trúc Lượng Giá Trị Hàng Hóa",
        "data": {
          "layers": [
            "W (Lượng giá trị hàng hóa)",
            "c (Giá trị tư liệu sản xuất đã tiêu hao - Giá trị cũ)",
            "v + m (Giá trị mới do lao động sống tạo ra)"
          ],
          "note": "W = c + v + m"
        }
      },
      {
        "type": "vs-wrap",
        "title": "Quy Luật Cung - Cầu",
        "data": {
          "left": {
            "title": "Cung > Cầu",
            "points": [
              "Giá cả < Giá trị",
              "Người bán thiệt, người mua lợi",
              "Sản xuất thu hẹp, vốn dịch chuyển sang ngành khác"
            ]
          },
          "right": {
            "title": "Cung < Cầu",
            "points": [
              "Giá cả > Giá trị",
              "Người bán lợi, người mua thiệt",
              "Sản xuất mở rộng, thu hút vốn đầu tư"
            ]
          }
        }
      },
      {
        "type": "quadrant",
        "title": "Ma Trận Quy Luật Cạnh Tranh",
        "data": {
          "xAxis": "Phạm vi",
          "yAxis": "Tính chất",
          "quadrants": [
            {
              "name": "Cạnh tranh trong nội bộ ngành",
              "desc": "Giữa các xí nghiệp cùng sản xuất 1 loại hàng hóa -> Hình thành giá trị xã hội."
            },
            {
              "name": "Cạnh tranh giữa các ngành",
              "desc": "Giữa các xí nghiệp ở các ngành khác nhau -> Hình thành tỷ suất lợi nhuận bình quân (p')."
            },
            {
              "name": "Cạnh tranh hoàn hảo",
              "desc": "Nhiều người mua, nhiều người bán, không ai chi phối được giá."
            },
            {
              "name": "Cạnh tranh không hoàn hảo (Độc quyền)",
              "desc": "Một hoặc vài doanh nghiệp chi phối sản lượng và giá cả."
            }
          ]
        }
      },
      {
        "type": "mindmap",
        "title": "Quy Luật Giá Trị Thặng Dư - Quy luật kinh tế tuyệt đối của CNTB",
        "data": {
          "root": "Giá trị thặng dư (m)",
          "branches": [
            {
              "name": "Bản chất",
              "details": [
                "Bộ phận giá trị mới dôi ra ngoài giá trị sức lao động",
                "Bị nhà tư bản chiếm không"
              ]
            },
            {
              "name": "Mục đích",
              "details": [
                "Tối đa hóa giá trị thặng dư",
                "Động lực thúc đẩy sản xuất tư bản chủ nghĩa"
              ]
            },
            {
              "name": "Phương pháp sản xuất",
              "details": [
                "GTTD Tuyệt đối (Kéo dài ngày lao động)",
                "GTTD Tương đối (Rút ngắn thời gian lao động tất yếu)"
              ]
            }
          ]
        }
      },
      {
        "type": "formula",
        "title": "Tỷ Suất & Khối Lượng Giá Trị Thặng Dư",
        "data": {
          "equation": "m' = (m / v) × 100% | M = m' × V",
          "variables": [
            {
              "symbol": "m'",
              "meaning": "Tỷ suất giá trị thặng dư (Đo trình độ bóc lột)"
            },
            {
              "symbol": "m",
              "meaning": "Giá trị thặng dư"
            },
            {
              "symbol": "v",
              "meaning": "Tư bản khả biến (giá trị sức lao động)"
            },
            {
              "symbol": "M",
              "meaning": "Khối lượng giá trị thặng dư (Đo quy mô bóc lột)"
            },
            {
              "symbol": "V",
              "meaning": "Tổng tư bản khả biến được sử dụng"
            }
          ],
          "note": "Ngày lao động = Thời gian lao động tất yếu (t) + Thời gian lao động thặng dư (t'). m' = (t' / t) × 100%"
        }
      },
      {
        "type": "vs-wrap",
        "title": "Phương Pháp Sản Xuất Giá Trị Thặng Dư",
        "data": {
          "left": {
            "title": "GTTD Tuyệt đối",
            "points": [
              "Kéo dài độ dài ngày lao động hoặc tăng cường độ lao động",
              "Thời gian lao động tất yếu không đổi",
              "Gặp giới hạn về thể chất con người và luật pháp"
            ]
          },
          "right": {
            "title": "GTTD Tương đối",
            "points": [
              "Rút ngắn thời gian lao động tất yếu",
              "Độ dài ngày lao động không đổi",
              "Dựa trên cơ sở tăng năng suất lao động xã hội"
            ]
          }
        }
      },
      {
        "type": "venn",
        "title": "GTTD Tương Đối vs GTTD Siêu Ngạch",
        "data": {
          "left": {
            "title": "GTTD Tương đối",
            "desc": "Do tăng năng suất lao động xã hội, toàn bộ giai cấp tư sản thu được."
          },
          "right": {
            "title": "GTTD Siêu ngạch",
            "desc": "Do tăng năng suất lao động cá biệt, chỉ nhà tư bản tiên tiến thu được (hình thức biến tướng)."
          },
          "intersection": "Đều dựa trên cơ sở tăng năng suất lao động, rút ngắn thời gian lao động tất yếu."
        }
      },
      {
        "type": "quadrant",
        "title": "Ma Trận Phân Chia Tư Bản",
        "data": {
          "xAxis": "Theo vai trò tạo ra m",
          "yAxis": "Theo phương thức chu chuyển",
          "quadrants": [
            {
              "name": "Tư bản bất biến (c)",
              "desc": "Giá trị không biến đổi về lượng trong quá trình sản xuất (Máy móc, nhà xưởng, nguyên liệu)."
            },
            {
              "name": "Tư bản khả biến (v)",
              "desc": "Bộ phận tư bản biến đổi về lượng, tạo ra m (Tiền lương trả cho công nhân)."
            },
            {
              "name": "Tư bản cố định (c1)",
              "desc": "Chu chuyển dần dần từng phần (Máy móc, thiết bị, nhà xưởng)."
            },
            {
              "name": "Tư bản lưu động (c2 + v)",
              "desc": "Chu chuyển toàn phần trong 1 chu kỳ (Nguyên nhiên vật liệu + Tiền lương)."
            }
          ]
        }
      },
      {
        "type": "cycle",
        "title": "Quy Luật Tích Lũy Tư Bản",
        "data": {
          "steps": [
            "Sản xuất ra giá trị thặng dư (m).",
            "Tư bản hóa một phần giá trị thặng dư (Biến m thành tư bản phụ thêm).",
            "Tái sản xuất mở rộng, tăng quy mô tư bản.",
            "Dẫn đến Tích tụ và Tập trung tư bản."
          ]
        }
      },
      {
        "type": "features",
        "title": "Hệ Quả Của Quy Luật Tích Lũy Tư Bản",
        "data": {
          "items": [
            {
              "name": "Tăng cấu tạo hữu cơ tư bản (c/v)",
              "desc": "Bộ phận tư bản bất biến (c) tăng nhanh hơn tư bản khả biến (v)."
            },
            {
              "name": "Gia tăng nạn nhân khẩu thừa",
              "desc": "Tình trạng thất nghiệp do cấu tạo hữu cơ tăng, sức hút lao động tương đối giảm."
            },
            {
              "name": "Phân hóa giàu nghèo sâu sắc",
              "desc": "Sự bần cùng hóa của giai cấp vô sản (Tuyệt đối và Tương đối)."
            }
          ]
        }
      },
      {
        "type": "mindmap",
        "title": "Quy Luật Độc Quyền & Cạnh Tranh Độc Quyền",
        "data": {
          "root": "Độc quyền",
          "branches": [
            {
              "name": "Nguyên nhân",
              "details": [
                "Tích tụ và tập trung sản xuất cao độ",
                "Sự phát triển của LLSX và công nghệ",
                "Khủng hoảng kinh tế và tín dụng"
              ]
            },
            {
              "name": "Bản chất",
              "details": [
                "Sự liên minh giữa các doanh nghiệp lớn",
                "Nắm được vị thế chi phối để thu lợi nhuận độc quyền cao"
              ]
            },
            {
              "name": "Các hình thức cơ bản",
              "details": [
                "Cartel (Cácten)",
                "Syndicate (Xanhđica)",
                "Trust (Tờ-rớt)",
                "Consortium (Công-xoóc-xi-ôm)"
              ]
            }
          ]
        }
      },
      {
        "type": "vs-wrap",
        "title": "Lợi Nhuận Bình Quân vs Lợi Nhuận Độc Quyền Cao",
        "data": {
          "left": {
            "title": "Lợi nhuận bình quân (p_ngang)",
            "points": [
              "Gắn với CNTB tự do cạnh tranh",
              "Kết quả của cạnh tranh giữa các ngành",
              "Hình thành Giá cả sản xuất (k + p_ngang)"
            ]
          },
          "right": {
            "title": "Lợi nhuận độc quyền cao",
            "points": [
              "Gắn với CNTB độc quyền",
              "Đạt được thông qua giá cả độc quyền (cao khi bán, thấp khi mua)",
              "Nguồn gốc từ m của công nhân, một phần p của tư bản nhỏ, giá trị từ lao động ở thuộc địa"
            ]
          }
        }
      },
      {
        "type": "onion",
        "title": "Chuyển Hóa Của Quy Luật Giá Trị Qua Các Giai Đoạn",
        "data": {
          "layers": [
            "Quy luật Giá Trị (SX Hàng hóa giản đơn: Giá cả xoay quanh Giá trị)",
            "Quy luật Giá Cả Sản Xuất (CNTB tự do cạnh tranh: Giá cả thị trường xoay quanh Giá cả SX = k + p_ngang)",
            "Quy luật Giá Cả Độc Quyền (CNTB Độc quyền: Chi phối thị trường, không thủ tiêu quy luật giá trị mà là hình thức biểu hiện mới)"
          ],
          "note": "Tổng giá cả vẫn = Tổng giá trị."
        }
      }
    ]
  },
  {
    "title": "Chuyên đề 3: Sự Tiến Hóa Của Nền Sản Xuất & Hàng Hóa",
    "blocks": [
      {
        "type": "vs-wrap",
        "title": "Sản Xuất Tự Nhiên vs Sản Xuất Hàng Hóa",
        "data": {
          "left": {
            "title": "Sản xuất tự nhiên",
            "points": [
              "Sản xuất để tự tiêu dùng",
              "Mục đích: Thỏa mãn nhu cầu trực tiếp của người sản xuất",
              "Quy mô: Nhỏ lẻ, khép kín, kỹ thuật thủ công",
              "Phân công lao động: Chưa phát triển"
            ]
          },
          "right": {
            "title": "Sản xuất hàng hóa",
            "points": [
              "Sản xuất để trao đổi, mua bán",
              "Mục đích: Phục vụ nhu cầu xã hội, người mua",
              "Quy mô: Lớn, mở rộng, kỹ thuật tiên tiến",
              "Phân công lao động: Xã hội hóa cao"
            ]
          }
        }
      },
      {
        "type": "onion",
        "title": "Cấu Trúc Hàng Hóa & Các Cấp Độ",
        "data": {
          "layers": [
            "Thực thể giá trị (Lao động trừu tượng kết tinh)",
            "Giá trị (Lao động xã hội của người sản xuất)",
            "Lượng giá trị (Thời gian lao động xã hội cần thiết)",
            "Giá trị sử dụng (Công dụng của vật phẩm)"
          ]
        }
      },
      {
        "type": "timeline",
        "title": "Lịch Sử Phát Triển Của Hình Thái Giá Trị",
        "data": {
          "events": [
            {
              "title": "Hình thái giản đơn / Ngẫu nhiên",
              "description": "Trao đổi trực tiếp vật lấy vật, tỷ lệ trao đổi mang tính ngẫu nhiên (VD: 1 con cừu = 2 cái rìu)."
            },
            {
              "title": "Hình thái mở rộng (Toàn bộ)",
              "description": "Một hàng hóa được biểu hiện giá trị ở nhiều hàng hóa khác nhau (1 con cừu = 2 cái rìu hoặc 1 mớ lúa hoặc...)."
            },
            {
              "title": "Hình thái chung",
              "description": "Nhiều hàng hóa cùng biểu hiện giá trị ở một hàng hóa đóng vai trò vật ngang giá chung."
            },
            {
              "title": "Hình thái tiền tệ",
              "description": "Vàng (hoặc bạc) độc chiếm vị trí vật ngang giá chung, đánh dấu sự ra đời của tiền."
            }
          ]
        }
      },
      {
        "type": "features",
        "title": "5 Chức Năng Của Tiền Tệ",
        "data": {
          "items": [
            {
              "title": "Thước đo giá trị",
              "description": "Đo lường, biểu hiện giá trị của các hàng hóa khác (giá cả)."
            },
            {
              "title": "Phương tiện lưu thông",
              "description": "Tiền làm môi giới trong quá trình trao đổi hàng hóa (H-T-H)."
            },
            {
              "title": "Phương tiện cất trữ",
              "description": "Tiền rút khỏi lưu thông, cất giữ dưới dạng vàng bạc để bảo toàn của cải."
            },
            {
              "title": "Phương tiện thanh toán",
              "description": "Chi trả cho hàng hóa mua chịu, nộp thuế, trả nợ."
            },
            {
              "title": "Tiền tệ thế giới",
              "description": "Thanh toán quốc tế giữa các quốc gia."
            }
          ]
        }
      },
      {
        "type": "vs-wrap",
        "title": "Công Thức Chung Của Tư Bản vs Lưu Thông Giản Đơn",
        "data": {
          "left": {
            "title": "Lưu thông giản đơn (H-T-H)",
            "points": [
              "Bắt đầu bằng Hàng, kết thúc bằng Hàng",
              "Mục đích: Giá trị sử dụng",
              "Quá trình có giới hạn (kết thúc khi nhu cầu thỏa mãn)"
            ]
          },
          "right": {
            "title": "Công thức tư bản (T-H-T')",
            "points": [
              "Bắt đầu bằng Tiền, kết thúc bằng Tiền (lớn hơn)",
              "Mục đích: Giá trị và Giá trị thặng dư (T' = T + ΔT)",
              "Quá trình vô giới hạn (lòng tham không đáy)"
            ]
          }
        }
      },
      {
        "type": "quadrant",
        "title": "Hàng Hóa Sức Lao Động",
        "data": {
          "topLeft": {
            "title": "Điều kiện 1",
            "description": "Người lao động được tự do về thân thể."
          },
          "topRight": {
            "title": "Điều kiện 2",
            "description": "Người lao động bị tước đoạt hết tư liệu sản xuất."
          },
          "bottomLeft": {
            "title": "Giá trị",
            "description": "Bằng giá trị các tư liệu sinh hoạt cần thiết để tái sản xuất sức lao động."
          },
          "bottomRight": {
            "title": "Giá trị sử dụng",
            "description": "Đặc biệt: Khi sử dụng, tạo ra giá trị mới lớn hơn giá trị của bản thân nó (nguồn gốc giá trị thặng dư)."
          }
        }
      },
      {
        "type": "mindmap",
        "title": "3 Phương Pháp Sản Xuất Giá Trị Thặng Dư",
        "data": {
          "nodes": [
            {
              "id": "root",
              "title": "Sản xuất GTTD",
              "children": [
                {
                  "id": "tuyet-doi",
                  "title": "Tuyệt đối",
                  "description": "Kéo dài ngày lao động vượt quá thời gian lao động tất yếu, giữ nguyên năng suất."
                },
                {
                  "id": "tuong-doi",
                  "title": "Tương đối",
                  "description": "Rút ngắn thời gian lao động tất yếu nhờ tăng năng suất lao động xã hội, giữ nguyên độ dài ngày lao động."
                },
                {
                  "id": "sieu-ngach",
                  "title": "Siêu ngạch",
                  "description": "Phần GTTD dôi ra nhờ áp dụng kỹ thuật mới làm cho giá trị cá biệt thấp hơn giá trị xã hội."
                }
              ]
            }
          ]
        }
      },
      {
        "type": "cycle",
        "title": "Tuần Hoàn Của Tư Bản (T - H - T')",
        "data": {
          "steps": [
            "Giai đoạn 1: Lưu thông (T - H). Tư bản tiền tệ chuyển thành tư bản sản xuất (mua TLSX và SLĐ).",
            "Giai đoạn 2: Sản xuất (H ... SX ... H'). Tư bản sản xuất biến thành tư bản hàng hóa mang giá trị thặng dư.",
            "Giai đoạn 3: Lưu thông (H' - T'). Bán hàng, tư bản hàng hóa biến lại thành tư bản tiền tệ (lớn hơn ban đầu)."
          ]
        }
      },
      {
        "type": "pyramid",
        "title": "Cấu Tạo Của Tư Bản",
        "data": {
          "levels": [
            "Cấu tạo hữu cơ (c/v): Cấu tạo giá trị phản ánh sự thay đổi của cấu tạo kỹ thuật",
            "Cấu tạo kỹ thuật: Tỷ lệ giữa số lượng TLSX và số lượng lao động",
            "Cấu tạo giá trị: Tỷ lệ giữa Tư bản bất biến (c) và Tư bản khả biến (v)"
          ]
        }
      },
      {
        "type": "flowchart",
        "title": "Nguồn Gốc Của Tích Lũy Tư Bản",
        "data": {
          "steps": [
            {
              "id": "gttd",
              "label": "Giá trị thặng dư (m)"
            },
            {
              "id": "tieu-dung",
              "label": "Tư bản tiêu dùng (m1)"
            },
            {
              "id": "tich-luy",
              "label": "Tích lũy tư bản (m2 - biến thành tư bản phụ thêm)"
            },
            {
              "id": "tai-sx",
              "label": "Tái sản xuất mở rộng quy mô"
            }
          ],
          "edges": [
            {
              "from": "gttd",
              "to": "tieu-dung"
            },
            {
              "from": "gttd",
              "to": "tich-luy"
            },
            {
              "from": "tich-luy",
              "to": "tai-sx"
            }
          ]
        }
      },
      {
        "type": "vs-wrap",
        "title": "Tích Tụ Tư Bản vs Tập Trung Tư Bản",
        "data": {
          "left": {
            "title": "Tích Tụ Tư Bản",
            "points": [
              "Tăng quy mô TB cá biệt nhờ tư bản hóa GTTD",
              "Làm tăng tổng quy mô tư bản của toàn xã hội",
              "Phản ánh trực tiếp mối quan hệ bóc lột giữa tư bản và lao động làm thuê"
            ]
          },
          "right": {
            "title": "Tập Trung Tư Bản",
            "points": [
              "Tăng quy mô TB cá biệt bằng cách sáp nhập các tư bản có sẵn",
              "Không làm tăng tổng quy mô tư bản toàn xã hội",
              "Phản ánh quan hệ cạnh tranh giữa các nhà tư bản"
            ]
          }
        }
      },
      {
        "type": "features",
        "title": "5 Đặc Điểm Kinh Tế Cơ Bản Của Chủ Nghĩa Độc Quyền",
        "data": {
          "items": [
            {
              "title": "Tập trung sản xuất",
              "description": "Tập trung sản xuất và sự hình thành các tổ chức độc quyền."
            },
            {
              "title": "Tư bản tài chính",
              "description": "Sự dung hợp giữa tư bản độc quyền ngân hàng và tư bản độc quyền công nghiệp."
            },
            {
              "title": "Xuất khẩu tư bản",
              "description": "Xuất khẩu tư bản (thay vì chỉ xuất khẩu hàng hóa) trở nên phổ biến."
            },
            {
              "title": "Phân chia thế giới về kinh tế",
              "description": "Sự hình thành các liên minh độc quyền quốc tế chia nhau thị trường thế giới."
            },
            {
              "title": "Phân chia thế giới về lãnh thổ",
              "description": "Các cường quốc đế quốc chủ nghĩa chia nhau đất đai thế giới."
            }
          ]
        }
      },
      {
        "type": "onion",
        "title": "Bản Chất Của Chủ Nghĩa Độc Quyền Nhà Nước",
        "data": {
          "layers": [
            "Sự kết hợp sức mạnh của Tổ chức độc quyền tư nhân và Nhà nước tư sản",
            "Bộ máy nhà nước phụ thuộc vào các tổ chức độc quyền",
            "Sự can thiệp của Nhà nước vào các quá trình kinh tế để bảo vệ lợi ích của tư bản độc quyền"
          ]
        }
      },
      {
        "type": "timeline",
        "title": "Các Cuộc Cách Mạng Công Nghiệp Trong Lịch Sử",
        "data": {
          "events": [
            {
              "title": "CMCN 1.0 (Cuối TK 18 - Đầu TK 19)",
              "description": "Động cơ hơi nước, cơ khí hóa, chuyển từ lao động thủ công sang máy móc."
            },
            {
              "title": "CMCN 2.0 (Nửa cuối TK 19 - Đầu TK 20)",
              "description": "Năng lượng điện, động cơ đốt trong, sản xuất dây chuyền hàng loạt."
            },
            {
              "title": "CMCN 3.0 (Thập niên 70 TK 20)",
              "description": "Máy tính, công nghệ thông tin, tự động hóa cục bộ."
            },
            {
              "title": "CMCN 4.0 (Đầu TK 21)",
              "description": "Hệ thống mạng vật lý (Cyber-Physical Systems), AI, IoT, Big Data."
            }
          ]
        }
      },
      {
        "type": "mindmap",
        "title": "Đặc Trưng Công Nghiệp Hóa, Hiện Đại Hóa Ở Việt Nam",
        "data": {
          "nodes": [
            {
              "id": "root",
              "title": "CNH, HĐH VN",
              "children": [
                {
                  "id": "nt1",
                  "title": "Mô hình",
                  "description": "Phát triển rút ngắn, gắn với kinh tế tri thức."
                },
                {
                  "id": "nt2",
                  "title": "Định hướng",
                  "description": "Kinh tế thị trường định hướng XHCN."
                },
                {
                  "id": "nt3",
                  "title": "Bối cảnh",
                  "description": "Hội nhập kinh tế quốc tế sâu rộng."
                }
              ]
            }
          ]
        }
      },
      {
        "type": "quadrant",
        "title": "Hội Nhập Kinh Tế Quốc Tế",
        "data": {
          "topLeft": {
            "title": "Cơ Hội",
            "description": "Mở rộng thị trường, thu hút vốn FDI, tiếp thu công nghệ và kỹ năng quản lý."
          },
          "topRight": {
            "title": "Thách Thức",
            "description": "Cạnh tranh gay gắt, nguy cơ tụt hậu, phụ thuộc kinh tế, rủi ro an ninh phi truyền thống."
          },
          "bottomLeft": {
            "title": "Bản Chất",
            "description": "Gắn kết kinh tế quốc gia với kinh tế khu vực và toàn cầu qua mở cửa."
          },
          "bottomRight": {
            "title": "Động Lực",
            "description": "Xu thế toàn cầu hóa và lực lượng sản xuất phát triển vượt biên giới quốc gia."
          }
        }
      },
      {
        "type": "pyramid",
        "title": "Các Mức Độ Hội Nhập Kinh Tế Quốc Tế",
        "data": {
          "levels": [
            "Liên hiệp kinh tế và tiền tệ (Vd: Eurozone - mức độ cao nhất)",
            "Thị trường chung (Common Market - tự do di chuyển vốn, lao động)",
            "Liên minh thuế quan (Customs Union - chung thuế quan với nước ngoài)",
            "Khu vực thương mại tự do (FTA - xóa bỏ thuế quan nội khối)",
            "Khu vực thương mại ưu đãi (PTA - giảm thuế quan)"
          ]
        }
      }
    ]
  },
  {
    "title": "Chuyên đề 4: Hệ Sinh Thái Các Chủ Thể & Vai Trò Của Nhà Nước",
    "blocks": [
      {
        "type": "mindmap",
        "title": "Hệ sinh thái các chủ thể trong nền kinh tế thị trường",
        "data": {
          "root": "Các chủ thể kinh tế",
          "children": [
            {
              "label": "Người sản xuất",
              "children": [
                "Cung cấp hàng hóa",
                "Tối đa hóa lợi nhuận",
                "Sử dụng yếu tố đầu vào"
              ]
            },
            {
              "label": "Người tiêu dùng",
              "children": [
                "Tiêu thụ sản phẩm",
                "Tối đa hóa hữu dụng",
                "Định hướng sản xuất"
              ]
            },
            {
              "label": "Chủ thể trung gian",
              "children": [
                "Kết nối cung cầu",
                "Môi giới, thương lái",
                "Giảm chi phí giao dịch"
              ]
            },
            {
              "label": "Nhà nước",
              "children": [
                "Quản lý vĩ mô",
                "Cung cấp hàng hóa công",
                "Khắc phục khuyết tật thị trường"
              ]
            }
          ]
        }
      },
      {
        "type": "vs-wrap",
        "title": "Người Sản Xuất vs Người Tiêu Dùng",
        "data": {
          "left": {
            "title": "Người sản xuất",
            "points": [
              "Cung cấp hàng hoá, dịch vụ",
              "Mục tiêu cốt lõi: Tối đa hóa lợi nhuận",
              "Trực tiếp tạo ra của cải vật chất",
              "Chịu rủi ro kinh doanh"
            ]
          },
          "right": {
            "title": "Người tiêu dùng",
            "points": [
              "Tiêu thụ hàng hoá, dịch vụ",
              "Mục tiêu cốt lõi: Tối đa hóa lợi ích/hữu dụng",
              "Người phán xử cuối cùng của thị trường",
              "Định hướng quy mô, cơ cấu sản xuất"
            ]
          }
        }
      },
      {
        "type": "matrix-table",
        "title": "Giai Cấp Tư Sản vs Giai Cấp Vô Sản",
        "data": {
          "headers": [
            "Tiêu chí",
            "Giai cấp Tư sản",
            "Giai cấp Vô sản"
          ],
          "rows": [
            [
              "Sở hữu TLSX",
              "Nắm giữ tư liệu sản xuất chủ yếu",
              "Không có tư liệu sản xuất"
            ],
            [
              "Vai trò kinh tế",
              "Tổ chức, bóc lột giá trị thặng dư",
              "Bán sức lao động, tạo ra GTTD"
            ],
            [
              "Lợi ích",
              "Tối đa hóa GTTD (m)",
              "Đấu tranh tăng tiền lương (v)"
            ],
            [
              "Vị thế xã hội",
              "Giai cấp thống trị",
              "Giai cấp bị trị"
            ]
          ]
        }
      },
      {
        "type": "quadrant",
        "title": "Tác Động Của Độc Quyền",
        "data": {
          "xAxis": "Tích cực / Tiêu cực",
          "yAxis": "Phạm vi hẹp / Phạm vi rộng",
          "quadrants": [
            {
              "label": "Tích cực - Vĩ mô",
              "items": [
                "Đẩy mạnh R&D",
                "Tăng khả năng cạnh tranh quốc tế"
              ]
            },
            {
              "label": "Tiêu cực - Vĩ mô",
              "items": [
                "Phân hóa giàu nghèo sâu sắc",
                "Thao túng chính trị, nhà nước"
              ]
            },
            {
              "label": "Tích cực - Vi mô",
              "items": [
                "Tối ưu quy mô",
                "Nâng cao năng suất lao động trong ngành"
              ]
            },
            {
              "label": "Tiêu cực - Vi mô",
              "items": [
                "Cạnh tranh không hoàn hảo",
                "Thiệt hại cho người tiêu dùng"
              ]
            }
          ]
        }
      },
      {
        "type": "onion",
        "title": "Cấu trúc Thể chế Kinh tế Thị trường Định hướng XHCN",
        "data": {
          "layers": [
            "Lõi: Sở hữu toàn dân (Nhà nước đại diện)",
            "Lớp 1: Kinh tế Nhà nước giữ vai trò chủ đạo",
            "Lớp 2: Đa dạng hình thức sở hữu, thành phần kinh tế",
            "Lớp 3: Hội nhập kinh tế quốc tế sâu rộng",
            "Vỏ ngoài: Sự quản lý của Nhà nước pháp quyền XHCN"
          ]
        }
      },
      {
        "type": "venn",
        "title": "Giao thoa lợi ích trong nền kinh tế",
        "data": {
          "sets": [
            {
              "name": "Lợi ích Cá nhân (Người LĐ)",
              "items": [
                "Tiền lương",
                "Đời sống"
              ]
            },
            {
              "name": "Lợi ích Tập thể (Doanh nghiệp)",
              "items": [
                "Lợi nhuận",
                "Thị phần"
              ]
            },
            {
              "name": "Lợi ích Xã hội (Nhà nước)",
              "items": [
                "Công bằng",
                "Tăng trưởng vĩ mô"
              ]
            }
          ],
          "intersections": [
            {
              "sets": [
                0,
                1
              ],
              "desc": "Hợp đồng lao động, thưởng năng suất"
            },
            {
              "sets": [
                1,
                2
              ],
              "desc": "Trách nhiệm xã hội, nộp thuế"
            },
            {
              "sets": [
                0,
                2
              ],
              "desc": "Phúc lợi xã hội, y tế, giáo dục"
            },
            {
              "sets": [
                0,
                1,
                2
              ],
              "desc": "Sự đồng thuận xã hội, phát triển bền vững"
            }
          ]
        }
      },
      {
        "type": "features",
        "title": "Vai trò của Nhà nước Pháp quyền XHCN",
        "data": {
          "items": [
            {
              "name": "Kiến tạo môi trường",
              "desc": "Xây dựng thể chế, luật pháp minh bạch, bảo vệ quyền tài sản."
            },
            {
              "name": "Điều tiết vĩ mô",
              "desc": "Sử dụng công cụ tài chính, tiền tệ để ổn định kinh tế, chống lạm phát."
            },
            {
              "name": "Phân phối lại thu nhập",
              "desc": "Điều tiết qua thuế và phúc lợi để giảm bất bình đẳng xã hội."
            },
            {
              "name": "Đảm bảo định hướng XHCN",
              "desc": "Kinh tế nhà nước dẫn dắt, phát triển vì con người."
            }
          ]
        }
      },
      {
        "type": "vs-wrap",
        "title": "Độc quyền Tư nhân vs Độc quyền Nhà nước",
        "data": {
          "left": {
            "title": "Độc quyền Tư nhân",
            "points": [
              "Phục vụ lợi ích tập đoàn",
              "Tối đa hóa siêu lợi nhuận độc quyền",
              "Thường kìm hãm cạnh tranh khốc liệt",
              "Có thể lũng đoạn nhà nước"
            ]
          },
          "right": {
            "title": "Độc quyền Nhà nước",
            "points": [
              "Phục vụ lợi ích quốc gia, xã hội",
              "Kiểm soát các ngành then chốt (điện, an ninh)",
              "Đảm bảo an sinh và ổn định vĩ mô",
              "Công cụ khắc phục thất bại thị trường"
            ]
          }
        }
      },
      {
        "type": "pyramid",
        "title": "Các Tầng Nấc Hội Nhập Kinh Tế Quốc Tế",
        "data": {
          "levels": [
            "Đỉnh: Liên minh Kinh tế và Tiền tệ (vd: EU)",
            "Tầng 3: Thị trường chung (Tự do di chuyển vốn, lao động)",
            "Tầng 2: Liên minh Thuế quan (Chính sách thuế chung)",
            "Tầng 1: Khu vực Thương mại Tự do (FTA)",
            "Đáy: Hợp tác thương mại song phương cơ bản"
          ]
        }
      },
      {
        "type": "hotspot",
        "title": "Chức Năng Của Chủ Thể Trung Gian",
        "data": {
          "image": "market_network",
          "spots": [
            {
              "label": "Kết nối",
              "desc": "Thu hẹp khoảng cách không gian, thời gian giữa cung và cầu."
            },
            {
              "label": "Giảm chi phí",
              "desc": "Giảm thiểu chi phí tìm kiếm thông tin, chi phí giao dịch."
            },
            {
              "label": "Chuyên môn hóa",
              "desc": "Giúp người sản xuất tập trung hoàn toàn vào khâu sản xuất."
            }
          ]
        }
      },
      {
        "type": "mindmap",
        "title": "Mô hình Kinh tế Thị trường Định hướng XHCN",
        "data": {
          "root": "KTTT Định hướng XHCN",
          "children": [
            {
              "label": "Mục tiêu",
              "children": [
                "Dân giàu, nước mạnh",
                "Dân chủ, công bằng, văn minh"
              ]
            },
            {
              "label": "Hình thức Sở hữu",
              "children": [
                "Sở hữu toàn dân",
                "Sở hữu tập thể",
                "Sở hữu tư nhân"
              ]
            },
            {
              "label": "Thành phần kinh tế",
              "children": [
                "KT Nhà nước (Chủ đạo)",
                "KT Tập thể",
                "KT Tư nhân (Động lực)",
                "KT FDI"
              ]
            },
            {
              "label": "Phân phối",
              "children": [
                "Theo lao động (Chủ yếu)",
                "Theo mức đóng góp vốn",
                "Phúc lợi xã hội"
              ]
            }
          ]
        }
      },
      {
        "type": "matrix-table",
        "title": "Các Công Cụ Điều Tiết Vĩ Mô Của Nhà Nước",
        "data": {
          "headers": [
            "Công cụ",
            "Mục đích",
            "Tác động chính"
          ],
          "rows": [
            [
              "Chính sách Thuế",
              "Tạo nguồn thu, phân phối lại",
              "Điều tiết sản xuất và tiêu dùng"
            ],
            [
              "Lãi suất",
              "Kiểm soát lượng tiền, lạm phát",
              "Kích thích hoặc kìm hãm đầu tư"
            ],
            [
              "Luật pháp",
              "Tạo sân chơi bình đẳng",
              "Bảo vệ quyền tài sản, hợp đồng"
            ],
            [
              "Kế hoạch hóa",
              "Định hướng phát triển",
              "Đảm bảo cân đối nền kinh tế"
            ]
          ]
        }
      },
      {
        "type": "features",
        "title": "Tính Tất Yếu Khách Quan Của Hội Nhập KTQT",
        "data": {
          "items": [
            {
              "name": "Toàn cầu hóa",
              "desc": "Là xu thế khách quan, không quốc gia nào có thể đứng ngoài."
            },
            {
              "name": "Phân công LĐ quốc tế",
              "desc": "Khai thác lợi thế so sánh, tối ưu nguồn lực."
            },
            {
              "name": "Cách mạng KH-CN",
              "desc": "Đòi hỏi nguồn vốn, công nghệ và thị trường rộng lớn hơn."
            },
            {
              "name": "Phát triển lực lượng SX",
              "desc": "Mở rộng không gian sinh tồn và phát triển cho nền kinh tế."
            }
          ]
        }
      },
      {
        "type": "onion",
        "title": "Bản Chất Của CNTB Độc Quyền Nhà Nước",
        "data": {
          "layers": [
            "Lõi: Bản chất bóc lột của Chủ nghĩa Tư bản",
            "Lớp 1: Sự thống trị của Tổ chức Độc quyền",
            "Lớp 2: Sự dung hợp tư bản độc quyền và nhà nước tư sản",
            "Vỏ ngoài: Can thiệp của nhà nước cứu vãn khủng hoảng"
          ]
        }
      },
      {
        "type": "quadrant",
        "title": "Mô Hình Tích Lũy Tư Bản",
        "data": {
          "xAxis": "Tập trung tư bản / Tích tụ tư bản",
          "yAxis": "Thay đổi quy mô chung / Giữ nguyên quy mô chung",
          "quadrants": [
            {
              "label": "Tích tụ TB",
              "items": [
                "Tăng quy mô tư bản cá biệt",
                "Tăng quy mô tư bản xã hội"
              ]
            },
            {
              "label": "Tập trung TB",
              "items": [
                "Tăng quy mô TB cá biệt",
                "Không làm tăng quy mô TB xã hội"
              ]
            },
            {
              "label": "Động lực",
              "items": [
                "Cạnh tranh",
                "Giá trị thặng dư"
              ]
            },
            {
              "label": "Hệ quả",
              "items": [
                "Hình thành độc quyền",
                "Bần cùng hóa vô sản"
              ]
            }
          ]
        }
      },
      {
        "type": "venn",
        "title": "Sự thống nhất giữa Độc quyền và Cạnh tranh",
        "data": {
          "sets": [
            {
              "name": "Độc quyền",
              "items": [
                "Thỏa hiệp",
                "Khống chế thị trường"
              ]
            },
            {
              "name": "Cạnh tranh",
              "items": [
                "Giành giật thị phần",
                "Tiêu diệt đối thủ"
              ]
            }
          ],
          "intersections": [
            {
              "sets": [
                0,
                1
              ],
              "desc": "Cạnh tranh giữa các tổ chức độc quyền; Cạnh tranh trong nội bộ độc quyền"
            }
          ]
        }
      }
    ]
  }
]